CHANGES.txt
MANIFEST.in
README.rst
TODOS.rst
setup.py
src/collective/__init__.py
src/collective.smsauthenticator.egg-info/PKG-INFO
src/collective.smsauthenticator.egg-info/SOURCES.txt
src/collective.smsauthenticator.egg-info/dependency_links.txt
src/collective.smsauthenticator.egg-info/entry_points.txt
src/collective.smsauthenticator.egg-info/namespace_packages.txt
src/collective.smsauthenticator.egg-info/not-zip-safe
src/collective.smsauthenticator.egg-info/requires.txt
src/collective.smsauthenticator.egg-info/top_level.txt
src/collective/smsauthenticator/__init__.py
src/collective/smsauthenticator/adapter.py
src/collective/smsauthenticator/configure.zcml
src/collective/smsauthenticator/helpers.py
src/collective/smsauthenticator/interfaces.py
src/collective/smsauthenticator/overrides.zcml
src/collective/smsauthenticator/pas_plugin.py
src/collective/smsauthenticator/profiles.zcml
src/collective/smsauthenticator/rebuild_i18n.sh
src/collective/smsauthenticator/setuphandlers.py
src/collective/smsauthenticator/testing.py
src/collective/smsauthenticator/userdataschema.py
src/collective/smsauthenticator/Extensions/Install.py
src/collective/smsauthenticator/Extensions/__init__.py
src/collective/smsauthenticator/browser/__init__.py
src/collective/smsauthenticator/browser/configure.zcml
src/collective/smsauthenticator/browser/controlpanel.py
src/collective/smsauthenticator/browser/disable_two_step_verification.py
src/collective/smsauthenticator/browser/disable_two_step_verification_for_all_users.py
src/collective/smsauthenticator/browser/enable_two_step_verification_for_all_users.py
src/collective/smsauthenticator/browser/helpers.py
src/collective/smsauthenticator/browser/list_user_ips.py
src/collective/smsauthenticator/browser/settings_helper.py
src/collective/smsauthenticator/browser/forms/__init__.py
src/collective/smsauthenticator/browser/forms/request_mobile_number_reset.py
src/collective/smsauthenticator/browser/forms/reset_mobile_number.py
src/collective/smsauthenticator/browser/forms/token.py
src/collective/smsauthenticator/browser/forms/user_setup_mobile_number.py
src/collective/smsauthenticator/browser/forms/user_setup_two_step_verification.py
src/collective/smsauthenticator/browser/static/main.css
src/collective/smsauthenticator/browser/static/main.js
src/collective/smsauthenticator/browser/templates/reset_mobile_number_succes.pt
src/collective/smsauthenticator/browser/templates/show_all_user_ips.pt
