Metadata-Version: 1.1
Name: collective.smsauthenticator
Version: 0.3.4
Summary: Two-step verification in Plone 4 using login codes sent by SMS.
Home-page: https://github.com/collective/collective.smsauthenticator
Author: Goldmund, Wyldebeast & Wunderliebe
Author-email: info@gw20e.com
License: GPL 2.0
Keywords: sms authenticator,two-step verification,multi-factor authentication,two-factor authentication
Platform: UNKNOWN
Classifier: Environment :: Web Environment
Classifier: Framework :: Plone
Classifier: Operating System :: OS Independent
Classifier: Programming Language :: Python
Classifier: Programming Language :: Python :: 2.6
Classifier: Programming Language :: Python :: 2.7
Classifier: Topic :: Software Development :: Libraries :: Python Modules
